inpip-0.1.1.dist-info/licenses/LICENSE
ipip/__init__.py
ipip/cli.py
ipip/config.py
ipip/emergency_undo.py
ipip/file_analyzer.py
ipip/file_context.py
ipip/file_operations.py
ipip/llm_resolver.py
ipip/ollama_installer.py
ipip/package_installer.py
ipip/package_searcher.py
ipip/requirements_manager.py
inpip-0.1.1.dist-info/METADATA
inpip-0.1.1.dist-info/WHEEL
inpip-0.1.1.dist-info/entry_points.txt
inpip-0.1.1.dist-info/top_level.txt
inpip-0.1.1.dist-info/RECORD
