Metadata-Version: 2.4
Name: inpip
Version: 0.1.1
Summary: Intelligent pip package installer using AI to resolve package names
Home-page: https://github.com/yourusername/ipip
Author: Cody Serino (Zero)
Author-email: "Cody Serino (Zero)" <iamtheoriginalzero@gmail.com>
License: MIT
Project-URL: Homepage, https://github.com/codyreign/ipip
Project-URL: Repository, https://github.com/codyreign/ipip
Project-URL: Issues, https://github.com/codyreign/ipip/issues
Keywords: pip,package,installer,ai,llm
Classifier: Development Status :: 3 - Alpha
Classifier: Intended Audience :: Developers
Classifier: License :: OSI Approved :: MIT License
Classifier: Programming Language :: Python :: 3
Classifier: Programming Language :: Python :: 3.8
Classifier: Programming Language :: Python :: 3.9
Classifier: Programming Language :: Python :: 3.10
Classifier: Programming Language :: Python :: 3.11
Classifier: Programming Language :: Python :: 3.12
Requires-Python: >=3.8
License-File: LICENSE
Requires-Dist: click>=8.0.0
Requires-Dist: requests>=2.25.0
Requires-Dist: rich>=10.0.0
Requires-Dist: packaging>=21.0
Provides-Extra: dev
Requires-Dist: pytest>=6.0; extra == "dev"
Requires-Dist: pytest-cov; extra == "dev"
Requires-Dist: black; extra == "dev"
Requires-Dist: flake8; extra == "dev"
Requires-Dist: mypy; extra == "dev"
Dynamic: author
Dynamic: home-page
Dynamic: license-file
Dynamic: requires-python
